{
	"info": {
		"_postman_id": "b8b73429-4f05-4e1a-9abf-ee3c4b4bd718",
		"name": "project endpoints",
		"schema": "https://schema.getpostman.com/json/collection/v2.1.0/collection.json",
		"_exporter_id": "23783527"
	},
	"item": [
		{
			"name": "register",
			"request": {
				"method": "POST",
				"header": [],
				"body": {
					"mode": "raw",
					"raw": "{\n    \"email\" : \"evgenij200121311\",\n    \"password\" : \"adsfasd\"\n}"
				},
				"url": {
					"raw": "{{base_url}}/v1/login",
					"host": [
						"{{base_url}}"
					],
					"path": [
						"v1",
						"login"
					]
				}
			},
			"response": []
		},
		{
			"name": "info",
			"protocolProfileBehavior": {
				"disableBodyPruning": true
			},
			"request": {
				"method": "GET",
				"header": [],
				"body": {
					"mode": "raw",
					"raw": "{\n    \"email\" : \"bebra228@mail.ru\",\n    \"password\" : \"qwerty1234\"\n}"
				},
				"url": {
					"raw": "{{base_url}}/v1/info",
					"host": [
						"{{base_url}}"
					],
					"path": [
						"v1",
						"info"
					]
				}
			},
			"response": []
		},
		{
			"name": "ebaloPsa",
			"request": {
				"method": "GET",
				"header": []
			},
			"response": []
		},
		{
			"name": "login",
			"request": {
				"method": "POST",
				"header": [],
				"body": {
					"mode": "raw",
					"raw": "{\n    \"email\" : \"evgenij200121311\",\n    \"password\" : \"adsfasd\"\n}"
				},
				"url": {
					"raw": "{{base_url}}/v1/login",
					"host": [
						"{{base_url}}"
					],
					"path": [
						"v1",
						"login"
					]
				}
			},
			"response": []
		},
		{
			"name": "logout",
			"request": {
				"auth": {
					"type": "bearer",
					"bearer": [
						{
							"key": "token",
							"value": "eyJhbGciOiJIUzI1NiIsInR5cCI6IkpXVCJ9.eyJleHAiOjE2Njg0NDc0NjksInN1YiI6ImV2Z2VuaWoyMDAxMjEzMSJ9.E4WUvBXJwWuiBAybFxXOsEHaRCCobmmgtu-Sna_RhYU",
							"type": "string"
						}
					]
				},
				"method": "POST",
				"header": [],
				"url": {
					"raw": "{{base_url}}/v1/logout",
					"host": [
						"{{base_url}}"
					],
					"path": [
						"v1",
						"logout"
					]
				}
			},
			"response": []
		}
	]
}